pyLabOn/LabReport.py
pyLabOn/__init__.py
pyLabOn/setup.py
pylabon-0.1.4.3.dist-info/LICENSE
pylabon-0.1.4.3.dist-info/METADATA
pylabon-0.1.4.3.dist-info/WHEEL
pylabon-0.1.4.3.dist-info/top_level.txt
pylabon-0.1.4.3.dist-info/RECORD
